quadrilateral_fitter/__init__.py
quadrilateral_fitter/_line.py
quadrilateral_fitter/quadrilateral_fitter.py
quadrilateral_fitter-1.11.dist-info/LICENSE
quadrilateral_fitter-1.11.dist-info/METADATA
quadrilateral_fitter-1.11.dist-info/WHEEL
quadrilateral_fitter-1.11.dist-info/top_level.txt
quadrilateral_fitter-1.11.dist-info/RECORD
