Metadata-Version: 2.1
Name: quadrilateral-fitter
Version: 1.11
Summary: QuadrilateralFitter is an efficient and easy-to-use Python library for fitting irregular quadrilaterals from irregular polygons or any noisy data.
Home-page: https://github.com/Eric-Canas/quadrilateral-fitter
Author: Eric-Canas
Author-email: eric@ericcanas.com
License: MIT
Keywords: quadrilateral,fitter,polygon,shape analysis,geometry
Platform: any
Classifier: Development Status :: 5 - Production/Stable
Classifier: License :: OSI Approved :: MIT License
Classifier: Programming Language :: Python
Classifier: Programming Language :: Python :: 3
Classifier: Operating System :: OS Independent
Classifier: Intended Audience :: Developers
Classifier: Intended Audience :: Science/Research
Classifier: Intended Audience :: Education
Classifier: Topic :: Software Development :: Libraries
Classifier: Topic :: Software Development :: Libraries :: Python Modules
Classifier: Topic :: Scientific/Engineering :: Mathematics
Classifier: Topic :: Scientific/Engineering :: Visualization
Classifier: Topic :: Scientific/Engineering :: Image Recognition
Classifier: Topic :: Scientific/Engineering :: Information Analysis
Classifier: Topic :: Scientific/Engineering :: Artificial Intelligence
Classifier: Topic :: Utilities
Requires-Python: >=3.6
License-File: LICENSE
Requires-Dist: shapely
Requires-Dist: numpy
Requires-Dist: scipy
